merge_mcp/__init__.py
merge_mcp/client.py
merge_mcp/constants.py
merge_mcp/main.py
merge_mcp/schema_index.py
merge_mcp/schema_parser.py
merge_mcp/scope_manager.py
merge_mcp/server.py
merge_mcp/services.py
merge_mcp/tool_manager.py
merge_mcp/types.py
merge_mcp-0.1.4.dist-info/METADATA
merge_mcp-0.1.4.dist-info/WHEEL
merge_mcp-0.1.4.dist-info/entry_points.txt
merge_mcp-0.1.4.dist-info/RECORD
